genuml/__init__.py
genuml/genuml.py
genuml-0.6.1.dist-info/entry_points.txt
genuml-0.6.1.dist-info/WHEEL
genuml-0.6.1.dist-info/METADATA
genuml-0.6.1.dist-info/RECORD
