Metadata-Version: 2.1
Name: genuml
Version: 0.6.1
Summary: Generate PlantUML diagram code from Java class files
Home-page: https://github.com/samuller/genuml
Keywords: plantuml,uml,java
Author: Simon Muller
Author-email: samullers@gmail.com
Requires-Python: >=3.6,<4.0
Classifier: Development Status :: 5 - Production/Stable
Classifier: Environment :: Console
Classifier: Intended Audience :: Developers
Classifier: Programming Language :: Python :: 3
Classifier: Programming Language :: Python :: 3 :: Only
Classifier: Programming Language :: Python :: 3.10
Classifier: Programming Language :: Python :: 3.6
Classifier: Programming Language :: Python :: 3.7
Classifier: Programming Language :: Python :: 3.8
Classifier: Programming Language :: Python :: 3.9
Classifier: Topic :: Multimedia :: Graphics :: Editors
Classifier: Topic :: Software Development :: Documentation
Requires-Dist: typer (>=0.4.0,<0.5.0)
Project-URL: Repository, https://github.com/samuller/genuml
